splashscreen_ctk/__init__.py
splashscreen_ctk-0.2.2.dist-info/LICENSE
splashscreen_ctk-0.2.2.dist-info/METADATA
splashscreen_ctk-0.2.2.dist-info/WHEEL
splashscreen_ctk-0.2.2.dist-info/top_level.txt
splashscreen_ctk-0.2.2.dist-info/RECORD
