Metadata-Version: 2.1
Name: splashscreen_ctk
Version: 0.2.2
Summary: Create a splash screen for a software, typically developed in custom tkinter
Author-email: DevDolphin7 <devdolphin7@outlook.com>
Project-URL: Homepage, https://github.com/DevDolphin7/SplashScreen
Classifier: Programming Language :: Python :: 3
Classifier: License :: OSI Approved :: GNU General Public License v3 (GPLv3)
Classifier: Operating System :: OS Independent
Requires-Python: >=3.8
License-File: LICENSE
Requires-Dist: customtkinter
